LICENSE
MANIFEST.in
README.rst
setup.cfg
setup.py
Flask_Lastuser.egg-info/PKG-INFO
Flask_Lastuser.egg-info/SOURCES.txt
Flask_Lastuser.egg-info/dependency_links.txt
Flask_Lastuser.egg-info/not-zip-safe
Flask_Lastuser.egg-info/requires.txt
Flask_Lastuser.egg-info/top_level.txt
flask_lastuser/__init__.py
flask_lastuser/sqlalchemy.py