Metadata-Version: 1.0
Name: Flask-Lastuser
Version: 0.3.6
Summary: Flask extension for Lastuser
Home-page: https://github.com/hasgeek/flask-lastuser
Author: Kiran Jonnalagadda
Author-email: kiran@hasgeek.in
License: BSD
Platform: any
Classifier: Development Status :: 4 - Beta
Classifier: Environment :: Web Environment
Classifier: Intended Audience :: Developers
Classifier: License :: OSI Approved :: BSD License
Classifier: Operating System :: OS Independent
Classifier: Programming Language :: Python
Classifier: Topic :: Internet :: WWW/HTTP :: Dynamic Content
Classifier: Topic :: Software Development :: Libraries :: Python Modules
